scania_truck_air_presure_fault_detector/VERSION
scania_truck_air_presure_fault_detector/__init__.py
scania_truck_air_presure_fault_detector/config.yml
scania_truck_air_presure_fault_detector/pipeline.py
scania_truck_air_presure_fault_detector/predict.py
scania_truck_air_presure_fault_detector/train_pipeline.py
scania_truck_air_presure_fault_detector/config/__init__.py
scania_truck_air_presure_fault_detector/config/core.py
scania_truck_air_presure_fault_detector/data_preprocessors/__init__.py
scania_truck_air_presure_fault_detector/data_preprocessors/preprocessors.py
scania_truck_air_presure_fault_detector/db_operations/__init__.py
scania_truck_air_presure_fault_detector/db_operations/service.py
scania_truck_air_presure_fault_detector/models/kmeans.pickle
scania_truck_air_presure_fault_detector/models/logistic_1.pickle
scania_truck_air_presure_fault_detector/models/random_forest_2.pickle
scania_truck_air_presure_fault_detector/models/scania_truck_fault_pipeline.pickle
scania_truck_air_presure_fault_detector/raw_files_validation/__init__.py
scania_truck_air_presure_fault_detector/raw_files_validation/validator.py
scania_truck_air_presure_fault_detector/train_data/data.csv
scania_truck_air_presure_fault_detector/training/__init__.py
scania_truck_air_presure_fault_detector/training/best_model_finder.py
scania_truck_air_presure_fault_detector/transform_data/__init__.py
scania_truck_air_presure_fault_detector/transform_data/data_transformer.py
scania_truck_air_presure_fault_detector/utils/__init__.py
scania_truck_air_presure_fault_detector/utils/file_management.py
scania_truck_air_presure_fault_detector/utils/helper.py
scania_truck_air_presure_fault_detector/utils/mlflow_helper.py
scania_truck_air_presure_fault_detector-0.1.0.dist-info/METADATA
scania_truck_air_presure_fault_detector-0.1.0.dist-info/WHEEL
scania_truck_air_presure_fault_detector-0.1.0.dist-info/top_level.txt
scania_truck_air_presure_fault_detector-0.1.0.dist-info/RECORD
