Metadata-Version: 2.1
Name: scania-truck-air-presure-fault-detector
Version: 0.1.0
Summary: classification model for scania truck air pressure fault detection.
Home-page: https://github.com/Damisss/defect_detection_in_air_presure_system_of_truck
Author: Damisss
Author-email: sam@sam.com
License: BSD-3
Platform: UNKNOWN
Classifier: License :: OSI Approved :: MIT License
Classifier: Programming Language :: Python
Classifier: Programming Language :: Python :: 3
Classifier: Programming Language :: Python :: 3.6
Classifier: Programming Language :: Python :: 3.7
Classifier: Programming Language :: Python :: 3.8
Classifier: Programming Language :: Python :: Implementation :: CPython
Classifier: Programming Language :: Python :: Implementation :: PyPy
Requires-Python: >=3.6.0
Requires-Dist: Flask (==2.0.2)
Requires-Dist: imbalanced-learn (==0.8.1)
Requires-Dist: matplotlib (==3.5.1)
Requires-Dist: pandas (==1.3.4)
Requires-Dist: kneed (==0.7.0)
Requires-Dist: mlflow (==1.22.0)
Requires-Dist: numpy (==1.21.4)
Requires-Dist: pydantic (==1.8.2)
Requires-Dist: pytest (==6.2.5)
Requires-Dist: scikit-learn (==1.0.1)
Requires-Dist: strictyaml (==1.6.1)
Requires-Dist: tox (==3.24.4)
Requires-Dist: pytest-cov (==3.0.0)
Requires-Dist: black (==20.8b1)
Requires-Dist: flake8 (<3.10.0,>=3.9.0)
Requires-Dist: mypy (==0.812)
Requires-Dist: isort (==5.8.0)
